visiongraph/AsyncGraphNode.py
visiongraph/BaseGraph.py
visiongraph/GraphNode.py
visiongraph/Processable.py
visiongraph/VisionGraph.py
visiongraph/VisionGraphBuilder.py
visiongraph/__init__.py
visiongraph/cache/__init__.py
visiongraph/data/Asset.py
visiongraph/data/LocalAsset.py
visiongraph/data/RepositoryAsset.py
visiongraph/data/__init__.py
visiongraph/data/labels/COCO.py
visiongraph/data/labels/DOTA.py
visiongraph/data/labels/__init__.py
visiongraph/dsp/BaseFilterNumpy.py
visiongraph/dsp/LandmarkSmoothFilter.py
visiongraph/dsp/OneEuroFilter.py
visiongraph/dsp/OneEuroFilterNumba.py
visiongraph/dsp/OneEuroFilterNumpy.py
visiongraph/dsp/VectorNumpySmoothFilter.py
visiongraph/dsp/__init__.py
visiongraph/estimator/BaseClassifier.py
visiongraph/estimator/BaseEstimator.py
visiongraph/estimator/BaseVisionEngine.py
visiongraph/estimator/ChainEstimator.py
visiongraph/estimator/ScoreThresholdEstimator.py
visiongraph/estimator/VisionClassifier.py
visiongraph/estimator/VisionEstimator.py
visiongraph/estimator/__init__.py
visiongraph/estimator/calculator/UndistortionCalculator.py
visiongraph/estimator/calculator/__init__.py
visiongraph/estimator/embedding/LandmarkEmbedder.py
visiongraph/estimator/embedding/__init__.py
visiongraph/estimator/embedding/knn/BaseKNNClassifier.py
visiongraph/estimator/embedding/knn/FaissKNNClassifier.py
visiongraph/estimator/embedding/knn/__init__.py
visiongraph/estimator/engine/InferenceEngineFactory.py
visiongraph/estimator/engine/__init__.py
visiongraph/estimator/inpaint/BaseInpainter.py
visiongraph/estimator/inpaint/GMCNNInpainter.py
visiongraph/estimator/inpaint/__init__.py
visiongraph/estimator/onnx/ONNXVisionEngine.py
visiongraph/estimator/onnx/__init__.py
visiongraph/estimator/openvino/OpenVinoEngine.py
visiongraph/estimator/openvino/OpenVinoObjectDetector.py
visiongraph/estimator/openvino/OpenVinoPoseEstimator.py
visiongraph/estimator/openvino/SyncInferencePipeline.py
visiongraph/estimator/openvino/__init__.py
visiongraph-1.1.0.1.dist-info/licenses/LICENSE
visiongraph-1.1.0.1.dist-info/METADATA
visiongraph-1.1.0.1.dist-info/WHEEL
visiongraph-1.1.0.1.dist-info/entry_points.txt
visiongraph-1.1.0.1.dist-info/top_level.txt
visiongraph-1.1.0.1.dist-info/RECORD
