Metadata-Version: 2.4
Name: visiongraph
Version: 1.1.0.1
Summary: Visiongraph is a high level computer vision framework.
Author-email: Florian Bruggisser <github@broox.ch>
License-Expression: MIT
Project-URL: Homepage, https://github.com/cansik/visiongraph
Project-URL: Documentation, https://cansik.github.io/visiongraph/
Project-URL: Repository, https://github.com/cansik/visiongraph.git
Classifier: Development Status :: 4 - Beta
Classifier: Intended Audience :: Developers
Classifier: Intended Audience :: Education
Classifier: Intended Audience :: Science/Research
Classifier: Operating System :: MacOS :: MacOS X
Classifier: Operating System :: Microsoft :: Windows
Classifier: Operating System :: POSIX :: Linux
Classifier: Programming Language :: Python :: 3 :: Only
Classifier: Topic :: Scientific/Engineering
Classifier: Topic :: Scientific/Engineering :: Image Processing
Classifier: Topic :: Scientific/Engineering :: Artificial Intelligence
Classifier: Topic :: Software Development
Classifier: Topic :: Software Development :: Libraries
Classifier: Topic :: Software Development :: Libraries :: Python Modules
Requires-Python: <3.13,>=3.10
License-File: LICENSE
Requires-Dist: requests
Requires-Dist: tqdm
Requires-Dist: vector~=1.6.2
Requires-Dist: scipy
Requires-Dist: numpy>2
Requires-Dist: opencv-python~=4.7.0; python_version <= "3.9"
Requires-Dist: opencv-python~=4.11; python_version > "3.9"
Provides-Extra: realsense
Requires-Dist: pyrealsense2-macosx~=2.54.2; platform_system == "Darwin" and extra == "realsense"
Requires-Dist: pyrealsense2~=2.55.1; platform_system != "Darwin" and extra == "realsense"
Provides-Extra: azure
Requires-Dist: pyk4a-bundle~=1.5; (platform_system == "Windows" or platform_system == "Linux") and extra == "azure"
Provides-Extra: depthai
Requires-Dist: depthai~=2.30; (platform_system != "Darwin" or platform_machine == "arm64") and extra == "depthai"
Provides-Extra: openvino
Requires-Dist: openvino~=2025.2.0; extra == "openvino"
Provides-Extra: mediapipe
Requires-Dist: mediapipe-numpy2~=0.10.21; extra == "mediapipe"
Provides-Extra: onnx
Requires-Dist: onnxruntime~=1.22.0; extra == "onnx"
Provides-Extra: onnx-gpu
Requires-Dist: onnxruntime~=1.22.0; platform_system == "Darwin" and extra == "onnx-gpu"
Requires-Dist: onnxruntime-gpu~=1.22.0; platform_system != "Darwin" and extra == "onnx-gpu"
Provides-Extra: onnx-directml
Requires-Dist: onnxruntime~=1.22.0; (platform_system == "Darwin" or platform_system == "Linux") and extra == "onnx-directml"
Requires-Dist: onnxruntime-directml~=1.22.0; platform_system == "Windows" and extra == "onnx-directml"
Provides-Extra: media
Requires-Dist: moviepy; extra == "media"
Requires-Dist: vidgear[core]; extra == "media"
Provides-Extra: numba
Requires-Dist: numba~=0.61; extra == "numba"
Provides-Extra: fbs
Requires-Dist: pyopengl; (platform_system == "Darwin" or platform_system == "Windows") and extra == "fbs"
Requires-Dist: syphon-python~=0.1.1; platform_system == "Darwin" and extra == "fbs"
Requires-Dist: SpoutGL~=0.1.1; platform_system == "Windows" and extra == "fbs"
Provides-Extra: faiss
Requires-Dist: faiss-cpu; extra == "faiss"
Provides-Extra: mot
Requires-Dist: filterpy; extra == "mot"
Dynamic: license-file
